week_1/alu_verilog/alu.v
//=========================================================
// Module      : ALU
// Description : 8-bit ALU to perform following operations:
//                1) Addition
//                2) Substraction
//                3) Logical AND
//                4) Logical OR
//                5) Logical XOR
//                6) Logical NOT
//                7) Logical Right Shift
//                8) Logical Left Shift
//
// Developer   : Mitu Raj
// Date        : July-2024
//=========================================================
module alu (
   input  wire [7:0] i_a     ,  // Input A
   input  wire [7:0] i_b     ,  // Input B
   input  wire [2:0] i_op    ,  // Opcode
   output reg  [7:0] o_res   ,  // Result
   output reg        o_carry    // Carry for add/substraction
);

// Operation decoding and result computation
always@(*) begin
   // Default value of carry
   o_carry = 1'b0 ;
   case (i_op) 
      3'b000 : begin  // ADD
         {o_carry, o_res} = {1'b0, i_a} + {1'b0, i_b} ;
      end
      3'b001 : begin  // SUB
         {o_carry, o_res} = {1'b0, i_a} - {1'b0, i_b} ;
      end
      3'b010 : begin  // AND
         o_res = i_a & i_b ;
      end
      3'b011 : begin  // OR
         o_res = i_a | i_b ;
      end
      3'b100 : begin  // XOR
         o_res = i_a ^ i_b ;
      end
      3'b101 : begin  // NOT (A)
         o_res = ~i_a ;
      end
      3'b110 : begin  // LRS by B
         o_res = i_a >> i_b[2:0] ;
      end
      3'b111 : begin  // LLS by B
         o_res = i_a << i_b[2:0] ;
      end
      default : ;
   endcase  
end

endmodule

week_1/alu_verilog/tb_alu.v
//=========================================================
// Module      : Testbench for ALU
// Description : Testbench to test all ALU features.
// Developer   : Mitu Raj
// Date        : July-2024
//=========================================================
// Time scale
`timescale 1ns/100ps

// Module definition
module tb_alu;
   // DUT signals
   reg  [7:0] dut_a     ;
   reg  [7:0] dut_b     ;
   reg  [2:0] dut_op    ;
   wire [7:0] dut_res   ;
   wire       dut_carry ;

   // Instantiate the ALU
   alu uut (
      .i_a     (dut_a)     ,
      .i_b     (dut_b)     ,
      .i_op    (dut_op)    ,
      .o_res   (dut_res)   ,
      .o_carry (dut_carry)
   );

   // VCD dump
   initial begin
      $dumpfile("./test_alu.vcd") ;
      $dumpvars(0, tb_alu)    ;
   end
   
   // Stimulus
   initial begin
      // Test Addition
      dut_a = 8'h0F; dut_b = 8'h01; dut_op = 3'b000 ;
      #10 ;

      // Test Subtraction
      dut_a = 8'h02; dut_b = 8'h03; dut_op = 3'b001 ;
      #10 ;

      // Test Logical AND
      dut_a = 8'h0F; dut_b = 8'hF0; dut_op = 3'b010 ;
      #10 ;

      // Test Logical OR
      dut_a = 8'h0F; dut_b = 8'hF0; dut_op = 3'b011 ;
      #10 ;

      // Test Logical XOR
      dut_a = 8'h0F; dut_b = 8'hF0; dut_op = 3'b100 ;
      #10 ;

      // Test Logical NOT
      dut_a = 8'h0F; dut_b = 8'h00; dut_op = 3'b101 ;
      #10 ;

      // Test Logical Right Shift
      dut_a = 8'h0F; dut_b = 8'h02; dut_op = 3'b110 ;
      #10 ;

      // Test Logical Left Shift
      dut_a = 8'h0F; dut_b = 8'h02; dut_op = 3'b111 ;
      #10 ;

      // End simulation
      $finish ;
   end
endmodule

week_1/alu_verilog/sim/test_alu.vcd
$date
	Tue Jul 30 02:49:04 2024
$end
$version
	Icarus Verilog
$end
$timescale
	100ps
$end
$scope module tb_alu $end
$var wire 8 ! dut_res [7:0] $end
$var wire 1 " dut_carry $end
$var reg 8 # dut_a [7:0] $end
$var reg 8 $ dut_b [7:0] $end
$var reg 3 % dut_op [2:0] $end
$scope module uut $end
$var wire 8 & i_a [7:0] $end
$var wire 8 ' i_b [7:0] $end
$var wire 3 ( i_op [2:0] $end
$var reg 1 " o_carry $end
$var reg 8 ) o_res [7:0] $end
$upscope $end
$upscope $end
$enddefinitions $end
#0
$dumpvars
b10000 )
b0 (
b1 '
b1111 &
b0 %
b1 $
b1111 #
0"
b10000 !
$end
#100
1"
b11111111 !
b11111111 )
b1 %
b1 (
b11 $
b11 '
b10 #
b10 &
#200
b0 !
b0 )
0"
b10 %
b10 (
b11110000 $
b11110000 '
b1111 #
b1111 &
#300
b11111111 !
b11111111 )
b11 %
b11 (
#400
b100 %
b100 (
#500
b11110000 !
b11110000 )
b101 %
b101 (
b0 $
b0 '
#600
b11 !
b11 )
b110 %
b110 (
b10 $
b10 '
#700
b111100 !
b111100 )
b111 %
b111 (
